egui_states/__init__.py
egui_states/server.py
egui_states/signals.py
egui_states/structures.py
egui_states/typing.py
egui_states/version.py
egui_states-0.8.2.dist-info/METADATA
egui_states-0.8.2.dist-info/WHEEL
egui_states-0.8.2.dist-info/licenses/LICENSE
egui_states-0.8.2.dist-info/RECORD
