Metadata-Version: 2.4
Name: egui-states
Version: 0.8.2
Summary: A Python library for egui-states project.
Author-email: Vojtech Homola <vojhom@outlook.cz>
License: MIT License
License-File: LICENSE
Requires-Python: >=3.12
Requires-Dist: numpy
